ditekmax/__init__.py
ditekmax/functions.py
ditekmax/greet.py
ditekmax-0.0.2.dist-info/LICENSE
ditekmax-0.0.2.dist-info/METADATA
ditekmax-0.0.2.dist-info/WHEEL
ditekmax-0.0.2.dist-info/top_level.txt
ditekmax-0.0.2.dist-info/RECORD
