Metadata-Version: 2.1
Name: ditekmax
Version: 0.0.2
Summary: PY LAB
Author: DITEK
Author-email: <maks.ditkovskiy.05@mail.ru>
Keywords: python,video,stream,video stream,camera stream,sockets
Classifier: Development Status :: 1 - Planning
Classifier: Intended Audience :: Developers
Classifier: Programming Language :: Python :: 3
Classifier: Operating System :: Unix
Classifier: Operating System :: MacOS :: MacOS X
Classifier: Operating System :: Microsoft :: Windows
License-File: LICENSE
